factom_py/__init__.py
factom_py/block_elements/__init__.py
factom_py/block_elements/admin_messages.py
factom_py/block_elements/balance_increase.py
factom_py/block_elements/chain.py
factom_py/block_elements/chain_commit.py
factom_py/block_elements/entry.py
factom_py/block_elements/entry_commit.py
factom_py/block_elements/factoid_transaction.py
factom_py/blockchains/__init__.py
factom_py/blockchains/base.py
factom_py/blockchains/pending_block.py
factom_py/blockchains/custom/__init__.py
factom_py/blockchains/custom/constants.py
factom_py/blockchains/local/__init__.py
factom_py/blockchains/local/constants.py
factom_py/blockchains/mainnet/__init__.py
factom_py/blockchains/mainnet/constants.py
factom_py/blockchains/mainnet/genesis.py
factom_py/blockchains/testnet/__init__.py
factom_py/blockchains/testnet/constants.py
factom_py/blockchains/testnet/genesis.py
factom_py/blocks/__init__.py
factom_py/blocks/admin_block.py
factom_py/blocks/directory_block.py
factom_py/blocks/entry_block.py
factom_py/blocks/entry_credit_block.py
factom_py/blocks/factoid_block.py
factom_py/db/__init__.py
factom_py/db/leveldb.py
factom_py/messages/__init__.py
factom_py/messages/ack.py
factom_py/messages/base.py
factom_py/messages/block_syncing.py
factom_py/messages/entry_syncing.py
factom_py/messages/heartbeat.py
factom_py/messages/missing_message.py
factom_py/messages/seals.py
factom_py/messages/server.py
factom_py/messages/transactions.py
factom_py/primitives/__init__.py
factom_py/primitives/signatures.py
factom_py/utils/__init__.py
factom_py/utils/filters.py
factom_py/utils/merkle.py
factom_py/utils/timestamp.py
factom_py/utils/varint.py
hydra/rpc/__init__.py
hydra/rpc/server.py
factom_py-0.1.4.dist-info/LICENSE
factom_py-0.1.4.dist-info/METADATA
factom_py-0.1.4.dist-info/WHEEL
factom_py-0.1.4.dist-info/top_level.txt
factom_py-0.1.4.dist-info/RECORD
